simplex_solver-3.1.0.dist-info/METADATA
simplex_solver-3.1.0.dist-info/WHEEL
simplexui/pysimplex.pyd
simplexui/pysimplex.dll.a
simplexui/_version.py
simplexui/__init__.py
simplexui/channelBox.py
simplexui/comboCheckDialog.py
simplexui/dragFilter.py
simplexui/falloffDialog.py
simplexui/interfaceModel.py
simplexui/interfaceModelTrees.py
simplexui/main.pyw
simplexui/simplexDialog.py
simplexui/travCheckDialog.py
simplexui/traversalDialog.py
simplexui/utils.py
simplexui/commands/__init__.py
simplexui/commands/alembicCommon.py
simplexui/commands/applyCorrectives.py
simplexui/commands/correctiveInterface.py
simplexui/commands/expandedExport.py
simplexui/commands/hdf5Convert.py
simplexui/commands/mayaCorrectiveInterface.py
simplexui/commands/mayatonumpy.py
simplexui/commands/mesh.py
simplexui/commands/numpytoimath.py
simplexui/commands/poseblendlib.py
simplexui/commands/reorderSimplexPoints.py
simplexui/commands/rigidAlign.py
simplexui/commands/smpxBlend.py
simplexui/commands/unsubdivide.py
simplexui/commands/uvTransfer.py
simplexui/img/ChefHead.png
simplexui/img/frozen.png
simplexui/interface/__init__.py
simplexui/interface/dummyInterface.py
simplexui/interface/mayaInterface.py
simplexui/items/__init__.py
simplexui/items/accessor.py
simplexui/items/combo.py
simplexui/items/falloff.py
simplexui/items/group.py
simplexui/items/progression.py
simplexui/items/shape.py
simplexui/items/simplex.py
simplexui/items/slider.py
simplexui/items/stack.py
simplexui/items/traversal.py
simplexui/menu/__init__.py
simplexui/menu/dummyPlugins/__init__.py
simplexui/menu/genericPlugins/__init__.py
simplexui/menu/genericPlugins/_builtins.py
simplexui/menu/genericPlugins/checkPossibleCombos.py
simplexui/menu/genericPlugins/exportSplit.py
simplexui/menu/genericPlugins/showFalloffs.py
simplexui/menu/genericPlugins/showTraversals.py
simplexui/menu/genericPlugins/simplexUvTransfer.py
simplexui/menu/genericPlugins/unsubdivide.py
simplexui/menu/mayaPlugins/__init__.py
simplexui/menu/mayaPlugins/exportOther.py
simplexui/menu/mayaPlugins/extractProgressives.py
simplex_solver-3.1.0.dist-info/RECORD
