Metadata-Version: 2.1
Name: simplex-solver
Version: 3.1.0
Summary: The Blur Studio Simplex Blendshape Combination System
Author-Email: Tyler Fox <tyler@blur.com>
Classifier: Programming Language :: Python :: 3.7
Classifier: Programming Language :: Python :: 3.8
Classifier: Programming Language :: Python :: 3.9
Classifier: Programming Language :: Python :: 3.10
Classifier: Programming Language :: Python :: Implementation :: CPython
Classifier: License :: OSI Approved :: GNU Lesser General Public License v3 (LGPLv3)
Classifier: Operating System :: Microsoft :: Windows
Classifier: Operating System :: POSIX :: Linux
Classifier: Operating System :: MacOS :: MacOS X
Project-URL: Project Page, https://github.com/blurstudio/simplex
Requires-Python: >=3.7
Requires-Dist: Qt.py
Provides-Extra: dev
Requires-Dist: tox; extra == "dev"
Requires-Dist: covdefaults; extra == "dev"
Requires-Dist: coverage; extra == "dev"
Requires-Dist: ruff; extra == "dev"
